{
  "last_updated": "2026-07-23T19:16:15.635502",
  "fukuoka": {
    "route": "TPE ⇄ FUK (福岡 5 天來回)",
    "average_price": 12001,
    "grid": [
      {
        "start": "2026-07-24",
        "end": "2026-07-28",
        "display": "07/24(五) ~ 07/28(二)",
        "tag": "週五~週二",
        "price": 11112,
        "airline": "預估航空",
        "stops": "直達"
      },
      {
        "start": "2026-07-30",
        "end": "2026-08-03",
        "display": "07/30(四) ~ 08/03(一)",
        "tag": "週四~週一",
        "price": 11834,
        "airline": "預估航空",
        "stops": "直達"
      },
      {
        "start": "2026-07-31",
        "end": "2026-08-04",
        "display": "07/31(五) ~ 08/04(二)",
        "tag": "週五~週二",
        "price": 12211,
        "airline": "預估航空",
        "stops": "直達"
      },
      {
        "start": "2026-08-06",
        "end": "2026-08-10",
        "display": "08/06(四) ~ 08/10(一)",
        "tag": "週四~週一",
        "price": 12617,
        "airline": "預估航空",
        "stops": "直達"
      },
      {
        "start": "2026-08-07",
        "end": "2026-08-11",
        "display": "08/07(五) ~ 08/11(二)",
        "tag": "週五~週二",
        "price": 13350,
        "airline": "預估航空",
        "stops": "直達"
      },
      {
        "start": "2026-08-13",
        "end": "2026-08-17",
        "display": "08/13(四) ~ 08/17(一)",
        "tag": "週四~週一",
        "price": 12016,
        "airline": "預估航空",
        "stops": "直達"
      },
      {
        "start": "2026-08-14",
        "end": "2026-08-18",
        "display": "08/14(五) ~ 08/18(二)",
        "tag": "週五~週二",
        "price": 12630,
        "airline": "預估航空",
        "stops": "直達"
      },
      {
        "start": "2026-08-20",
        "end": "2026-08-24",
        "display": "08/20(四) ~ 08/24(一)",
        "tag": "週四~週一",
        "price": 10176,
        "airline": "預估航空",
        "stops": "直達"
      },
      {
        "start": "2026-08-21",
        "end": "2026-08-25",
        "display": "08/21(五) ~ 08/25(二)",
        "tag": "週五~週二",
        "price": 11066,
        "airline": "預估航空",
        "stops": "直達"
      },
      {
        "start": "2026-08-27",
        "end": "2026-08-31",
        "display": "08/27(四) ~ 08/31(一)",
        "tag": "週四~週一",
        "price": 13175,
        "airline": "預估航空",
        "stops": "直達"
      },
      {
        "start": "2026-08-28",
        "end": "2026-09-01",
        "display": "08/28(五) ~ 09/01(二)",
        "tag": "週五~週二",
        "price": 11568,
        "airline": "預估航空",
        "stops": "直達"
      },
      {
        "start": "2026-09-03",
        "end": "2026-09-07",
        "display": "09/03(四) ~ 09/07(一)",
        "tag": "週四~週一",
        "price": 12563,
        "airline": "預估航空",
        "stops": "直達"
      },
      {
        "start": "2026-09-04",
        "end": "2026-09-08",
        "display": "09/04(五) ~ 09/08(二)",
        "tag": "週五~週二",
        "price": 12498,
        "airline": "預估航空",
        "stops": "直達"
      },
      {
        "start": "2026-09-10",
        "end": "2026-09-14",
        "display": "09/10(四) ~ 09/14(一)",
        "tag": "週四~週一",
        "price": 10892,
        "airline": "預估航空",
        "stops": "直達"
      },
      {
        "start": "2026-09-11",
        "end": "2026-09-15",
        "display": "09/11(五) ~ 09/15(二)",
        "tag": "週五~週二",
        "price": 12646,
        "airline": "預估航空",
        "stops": "直達"
      },
      {
        "start": "2026-09-17",
        "end": "2026-09-21",
        "display": "09/17(四) ~ 09/21(一)",
        "tag": "週四~週一",
        "price": 12735,
        "airline": "預估航空",
        "stops": "直達"
      },
      {
        "start": "2026-09-18",
        "end": "2026-09-22",
        "display": "09/18(五) ~ 09/22(二)",
        "tag": "週五~週二",
        "price": 12314,
        "airline": "預估航空",
        "stops": "直達"
      },
      {
        "start": "2026-09-24",
        "end": "2026-09-28",
        "display": "09/24(四) ~ 09/28(一)",
        "tag": "週四~週一",
        "price": 10986,
        "airline": "預估航空",
        "stops": "直達"
      },
      {
        "start": "2026-09-25",
        "end": "2026-09-29",
        "display": "09/25(五) ~ 09/29(二)",
        "tag": "週五~週二",
        "price": 13034,
        "airline": "預估航空",
        "stops": "直達"
      },
      {
        "start": "2026-10-01",
        "end": "2026-10-05",
        "display": "10/01(四) ~ 10/05(一)",
        "tag": "週四~週一",
        "price": 12110,
        "airline": "預估航空",
        "stops": "直達"
      },
      {
        "start": "2026-10-02",
        "end": "2026-10-06",
        "display": "10/02(五) ~ 10/06(二)",
        "tag": "週五~週二",
        "price": 12100,
        "airline": "預估航空",
        "stops": "直達"
      },
      {
        "start": "2026-10-08",
        "end": "2026-10-12",
        "display": "10/08(四) ~ 10/12(一)",
        "tag": "週四~週一",
        "price": 12173,
        "airline": "預估航空",
        "stops": "直達"
      },
      {
        "start": "2026-10-09",
        "end": "2026-10-13",
        "display": "10/09(五) ~ 10/13(二)",
        "tag": "週五~週二",
        "price": 11290,
        "airline": "預估航空",
        "stops": "直達"
      },
      {
        "start": "2026-10-15",
        "end": "2026-10-19",
        "display": "10/15(四) ~ 10/19(一)",
        "tag": "週四~週一",
        "price": 10931,
        "airline": "預估航空",
        "stops": "直達"
      }
    ]
  },
  "tokyo": {
    "route": "TPE ⇄ TYO (東京 5 天來回)",
    "average_price": 14944,
    "grid": [
      {
        "start": "2026-07-24",
        "end": "2026-07-28",
        "display": "07/24(五) ~ 07/28(二)",
        "tag": "週五~週二",
        "price": 13627,
        "airline": "預估航空",
        "stops": "直達"
      },
      {
        "start": "2026-07-30",
        "end": "2026-08-03",
        "display": "07/30(四) ~ 08/03(一)",
        "tag": "週四~週一",
        "price": 16411,
        "airline": "預估航空",
        "stops": "直達"
      },
      {
        "start": "2026-07-31",
        "end": "2026-08-04",
        "display": "07/31(五) ~ 08/04(二)",
        "tag": "週五~週二",
        "price": 14986,
        "airline": "預估航空",
        "stops": "直達"
      },
      {
        "start": "2026-08-06",
        "end": "2026-08-10",
        "display": "08/06(四) ~ 08/10(一)",
        "tag": "週四~週一",
        "price": 16163,
        "airline": "預估航空",
        "stops": "直達"
      },
      {
        "start": "2026-08-07",
        "end": "2026-08-11",
        "display": "08/07(五) ~ 08/11(二)",
        "tag": "週五~週二",
        "price": 17493,
        "airline": "預估航空",
        "stops": "直達"
      },
      {
        "start": "2026-08-13",
        "end": "2026-08-17",
        "display": "08/13(四) ~ 08/17(一)",
        "tag": "週四~週一",
        "price": 15021,
        "airline": "預估航空",
        "stops": "直達"
      },
      {
        "start": "2026-08-14",
        "end": "2026-08-18",
        "display": "08/14(五) ~ 08/18(二)",
        "tag": "週五~週二",
        "price": 15483,
        "airline": "預估航空",
        "stops": "直達"
      },
      {
        "start": "2026-08-20",
        "end": "2026-08-24",
        "display": "08/20(四) ~ 08/24(一)",
        "tag": "週四~週一",
        "price": 15558,
        "airline": "預估航空",
        "stops": "直達"
      },
      {
        "start": "2026-08-21",
        "end": "2026-08-25",
        "display": "08/21(五) ~ 08/25(二)",
        "tag": "週五~週二",
        "price": 14446,
        "airline": "預估航空",
        "stops": "直達"
      },
      {
        "start": "2026-08-27",
        "end": "2026-08-31",
        "display": "08/27(四) ~ 08/31(一)",
        "tag": "週四~週一",
        "price": 14687,
        "airline": "預估航空",
        "stops": "直達"
      },
      {
        "start": "2026-08-28",
        "end": "2026-09-01",
        "display": "08/28(五) ~ 09/01(二)",
        "tag": "週五~週二",
        "price": 16395,
        "airline": "預估航空",
        "stops": "直達"
      },
      {
        "start": "2026-09-03",
        "end": "2026-09-07",
        "display": "09/03(四) ~ 09/07(一)",
        "tag": "週四~週一",
        "price": 15014,
        "airline": "預估航空",
        "stops": "直達"
      },
      {
        "start": "2026-09-04",
        "end": "2026-09-08",
        "display": "09/04(五) ~ 09/08(二)",
        "tag": "週五~週二",
        "price": 15352,
        "airline": "預估航空",
        "stops": "直達"
      },
      {
        "start": "2026-09-10",
        "end": "2026-09-14",
        "display": "09/10(四) ~ 09/14(一)",
        "tag": "週四~週一",
        "price": 16098,
        "airline": "預估航空",
        "stops": "直達"
      },
      {
        "start": "2026-09-11",
        "end": "2026-09-15",
        "display": "09/11(五) ~ 09/15(二)",
        "tag": "週五~週二",
        "price": 14258,
        "airline": "預估航空",
        "stops": "直達"
      },
      {
        "start": "2026-09-17",
        "end": "2026-09-21",
        "display": "09/17(四) ~ 09/21(一)",
        "tag": "週四~週一",
        "price": 13386,
        "airline": "預估航空",
        "stops": "直達"
      },
      {
        "start": "2026-09-18",
        "end": "2026-09-22",
        "display": "09/18(五) ~ 09/22(二)",
        "tag": "週五~週二",
        "price": 15129,
        "airline": "預估航空",
        "stops": "直達"
      },
      {
        "start": "2026-09-24",
        "end": "2026-09-28",
        "display": "09/24(四) ~ 09/28(一)",
        "tag": "週四~週一",
        "price": 13980,
        "airline": "預估航空",
        "stops": "直達"
      },
      {
        "start": "2026-09-25",
        "end": "2026-09-29",
        "display": "09/25(五) ~ 09/29(二)",
        "tag": "週五~週二",
        "price": 14060,
        "airline": "預估航空",
        "stops": "直達"
      },
      {
        "start": "2026-10-01",
        "end": "2026-10-05",
        "display": "10/01(四) ~ 10/05(一)",
        "tag": "週四~週一",
        "price": 14164,
        "airline": "預估航空",
        "stops": "直達"
      },
      {
        "start": "2026-10-02",
        "end": "2026-10-06",
        "display": "10/02(五) ~ 10/06(二)",
        "tag": "週五~週二",
        "price": 13539,
        "airline": "預估航空",
        "stops": "直達"
      },
      {
        "start": "2026-10-08",
        "end": "2026-10-12",
        "display": "10/08(四) ~ 10/12(一)",
        "tag": "週四~週一",
        "price": 14455,
        "airline": "預估航空",
        "stops": "直達"
      },
      {
        "start": "2026-10-09",
        "end": "2026-10-13",
        "display": "10/09(五) ~ 10/13(二)",
        "tag": "週五~週二",
        "price": 13377,
        "airline": "預估航空",
        "stops": "直達"
      },
      {
        "start": "2026-10-15",
        "end": "2026-10-19",
        "display": "10/15(四) ~ 10/19(一)",
        "tag": "週四~週一",
        "price": 15591,
        "airline": "預估航空",
        "stops": "直達"
      }
    ]
  }
}